erlpack/__init__.py
erlpack/_packer.py
erlpack/_unpacker.py
erlpack/constants.py
erlpack/encoder.py
erlpack/types.py
pure_py_erlpack-1.0.0.dist-info/COPYING
pure_py_erlpack-1.0.0.dist-info/LICENSE
pure_py_erlpack-1.0.0.dist-info/METADATA
pure_py_erlpack-1.0.0.dist-info/WHEEL
pure_py_erlpack-1.0.0.dist-info/top_level.txt
pure_py_erlpack-1.0.0.dist-info/RECORD
